SiYuan/__init__.py
SiYuan/client.py
SiYuan/export_to_xmind.py
siyuan-0.1.2.dist-info/entry_points.txt
siyuan-0.1.2.dist-info/WHEEL
siyuan-0.1.2.dist-info/METADATA
siyuan-0.1.2.dist-info/RECORD
