Metadata-Version: 2.1
Name: siyuan
Version: 0.1.2
Summary: SiYuan Api Implement
License: MIT
Author: InEase
Author-email: InEase28@gmail.com
Requires-Python: >=3.8,<4.0
Classifier: License :: OSI Approved :: MIT License
Classifier: Programming Language :: Python :: 3
Classifier: Programming Language :: Python :: 3.10
Classifier: Programming Language :: Python :: 3.8
Classifier: Programming Language :: Python :: 3.9
